game.py
solve_mathematical_problems.py
solve_some_problems-0.1.0.dist-info/METADATA
solve_some_problems-0.1.0.dist-info/WHEEL
solve_some_problems-0.1.0.dist-info/top_level.txt
solve_some_problems-0.1.0.dist-info/RECORD
