Metadata-Version: 2.1
Name: solve-some-problems
Version: 0.1.0
Summary: Used to solve some problems.
Home-page: UNKNOWN
Author: UNKNOWN
Author-email: UNKNOWN
License: UNKNOWN
Platform: UNKNOWN
